setup.py
minimise_functions_gradient_descent_and_normal_equation/__init__.py
minimise_functions_gradient_descent_and_normal_equation/gradient_descent.py
minimise_functions_gradient_descent_and_normal_equation/minimise_function.py
minimise_functions_gradient_descent_and_normal_equation/normal_equation.py
minimise_functions_gradient_descent_and_normal_equation.egg-info/PKG-INFO
minimise_functions_gradient_descent_and_normal_equation.egg-info/SOURCES.txt
minimise_functions_gradient_descent_and_normal_equation.egg-info/dependency_links.txt
minimise_functions_gradient_descent_and_normal_equation.egg-info/top_level.txt
minimise_functions_gradient_descent_and_normal_equation.egg-info/zip-safe