Metadata-Version: 1.0
Name: minimise-functions-gradient-descent-and-normal-equation
Version: 0.1
Summary: A python package containing implementations of two widely used algorithms to minimise any function - Gradient Descent algorithm and the Normal Equation method.
Home-page: https://github.com/pypa/sampleproject
Author: UNKNOWN
Author-email: UNKNOWN
License: UNKNOWN
Platform: UNKNOWN
